{"title": [{"text": "d m Journal of Computational Linguistics Ameriean Journal of Computational Linguistics Microfiche 22 2 3", "labels": [], "entities": [{"text": "Ameriean Journal of Computational Linguistics Microfiche 22", "start_pos": 41, "end_pos": 100, "type": "DATASET", "confidence": 0.8532885653632027}]}], "abstractContent": [{"text": "Microfiche 22 THE FINITE STRING MEWSLETTER OF THE ASSOCIATION FOR COMPUTATIONAL LIINGUISTICS WDLUME 12-NUMBER 4 SEPTEMBER 1975' This issue of the Journal contains no bibliography beyond announcements of some new books; a re t s o-spective l i st from the Fondazione Dalle Mole, and two reviews.", "labels": [], "entities": [{"text": "Microfiche", "start_pos": 0, "end_pos": 10, "type": "DATASET", "confidence": 0.9297100305557251}, {"text": "THE FINITE STRING MEWSLETTER", "start_pos": 14, "end_pos": 42, "type": "METRIC", "confidence": 0.7033558636903763}, {"text": "WDLUME 12-NUMBER 4", "start_pos": 93, "end_pos": 111, "type": "METRIC", "confidence": 0.8371489842732748}, {"text": "SEPTEMBER", "start_pos": 112, "end_pos": 121, "type": "METRIC", "confidence": 0.5431227684020996}, {"text": "This issue of the Journal", "start_pos": 128, "end_pos": 153, "type": "DATASET", "confidence": 0.6931858062744141}]}, {"text": "The Ed it or has been away from his of f i c e and the former Ed i. to r i a 1 Assistant is now employed full time elsewhere.", "labels": [], "entities": []}, {"text": "Prospects for the next issue look good.", "labels": [], "entities": []}, {"text": "CAN JOURNAL OF COMPUTATIONAL LINGUISTICS is published the Members of the Ass~Ciation can submit suggestions to the chairman or any member of the Committee.", "labels": [], "entities": [{"text": "JOURNAL", "start_pos": 4, "end_pos": 11, "type": "METRIC", "confidence": 0.9849639534950256}, {"text": "COMPUTATIONAL LINGUISTICS", "start_pos": 15, "end_pos": 40, "type": "METRIC", "confidence": 0.7552536725997925}]}], "introductionContent": [], "datasetContent": [], "tableCaptions": []}