{"title": [{"text": "Thai National Corpus: A Progress Report", "labels": [], "entities": [{"text": "Thai National Corpus", "start_pos": 0, "end_pos": 20, "type": "DATASET", "confidence": 0.9190701047579447}]}], "abstractContent": [{"text": "This paper presents problems and solutions in developing Thai National Corpus (TNC).", "labels": [], "entities": [{"text": "Thai National Corpus (TNC)", "start_pos": 57, "end_pos": 83, "type": "DATASET", "confidence": 0.9277730882167816}]}, {"text": "TNC is designed to be a comparable corpus of Brit-ish National Corpus.", "labels": [], "entities": [{"text": "TNC", "start_pos": 0, "end_pos": 3, "type": "DATASET", "confidence": 0.9379114508628845}, {"text": "Brit-ish National Corpus", "start_pos": 45, "end_pos": 69, "type": "DATASET", "confidence": 0.9165706634521484}]}, {"text": "The project aims to collect eighty million words.", "labels": [], "entities": []}, {"text": "Since 2006, the project can now collect only fourteen million words.", "labels": [], "entities": []}, {"text": "The data is accessible from the TNC Web.", "labels": [], "entities": [{"text": "TNC Web", "start_pos": 32, "end_pos": 39, "type": "DATASET", "confidence": 0.9251108169555664}]}, {"text": "Delay in creating the TNC is mainly caused from obtaining authorization of copyright texts.", "labels": [], "entities": []}, {"text": "Methods used for collecting data and the results are discussed.", "labels": [], "entities": []}, {"text": "Errors during the process of encoding data and how to handle these errors will be described.", "labels": [], "entities": []}], "introductionContent": [], "datasetContent": [], "tableCaptions": []}