{"title": [{"text": "CUNY-PKU Parser at SemEval-2019 Task 1: Cross-lingual Semantic Parsing with UCCA", "labels": [], "entities": [{"text": "CUNY-PKU Parser", "start_pos": 0, "end_pos": 15, "type": "DATASET", "confidence": 0.8763346076011658}, {"text": "Semantic Parsing", "start_pos": 54, "end_pos": 70, "type": "TASK", "confidence": 0.6801570504903793}, {"text": "UCCA", "start_pos": 76, "end_pos": 80, "type": "DATASET", "confidence": 0.843239426612854}]}], "abstractContent": [{"text": "This paper describes the systems of the CUNY-PKU team in \"SemEval 2019 Task 1: Cross-lingual Semantic Parsing with UCCA\" 1.", "labels": [], "entities": [{"text": "SemEval 2019 Task 1", "start_pos": 58, "end_pos": 77, "type": "TASK", "confidence": 0.9073683023452759}]}, {"text": "We introduce a novel model by applying a cascaded MLP and BiLSTM model.", "labels": [], "entities": [{"text": "BiLSTM", "start_pos": 58, "end_pos": 64, "type": "METRIC", "confidence": 0.9748308062553406}]}, {"text": "Then, we ensemble multiple system-outputs by repars-ing.", "labels": [], "entities": []}, {"text": "In particular, we introduce anew decoding algorithm for building the UCCA representation.", "labels": [], "entities": []}, {"text": "Our system won the first place in one track (French-20K-Open), second places in four tracks (English-Wiki-Open, English-20K-Open, German-20K-Open, and German-20K-Closed), and third place in one track (English-20K-Closed), among all seven tracks.", "labels": [], "entities": []}], "introductionContent": [{"text": "We participate in all seven tracks in Cross-lingual Semantic Parsing at SemEval 2019.", "labels": [], "entities": [{"text": "Cross-lingual Semantic Parsing", "start_pos": 38, "end_pos": 68, "type": "TASK", "confidence": 0.6655629873275757}]}, {"text": "Our submission systems 2 are based on BiLSTM using TUPA (.", "labels": [], "entities": []}, {"text": "Then, we built a second single parser using BiL-STM (Bi-directional LSTM) and Multi-Layer Perceptron (MLP) with TUPA ().", "labels": [], "entities": [{"text": "TUPA", "start_pos": 112, "end_pos": 116, "type": "METRIC", "confidence": 0.6030392050743103}]}, {"text": "Most importantly, we introduce anew model Cascaded BiLSTM by first pre-training the BiLSTM and MLP model and then to continue training another MLP model.", "labels": [], "entities": []}, {"text": "The cascaded BiLSTM parser significantly enhances the parsing accuracy on all tasks.", "labels": [], "entities": [{"text": "BiLSTM parser", "start_pos": 13, "end_pos": 26, "type": "TASK", "confidence": 0.5769785046577454}, {"text": "parsing", "start_pos": 54, "end_pos": 61, "type": "TASK", "confidence": 0.960142970085144}, {"text": "accuracy", "start_pos": 62, "end_pos": 70, "type": "METRIC", "confidence": 0.9461888074874878}]}, {"text": "We also complete a SelfAttentive Constituency Parser ( as comparison.", "labels": [], "entities": []}, {"text": "Finally, we ensemble different parsers with a reparsing strategy ().", "labels": [], "entities": []}, {"text": "In particular, we introduce a novel algorithm based on dynamic programming to perform inference for the UCCA representation.", "labels": [], "entities": []}, {"text": "This 1 https://competitions.codalab.org/ competitions/19160 2 https://github.com/weimin17/ semEval-taks1 decoder can also be utilized as a core engine fora single parser.", "labels": [], "entities": []}, {"text": "In the post-evaluation stage, our improved systems are ranked first in three tracks and second in the other four tracks.", "labels": [], "entities": []}, {"text": "A shared task summary paper ( by competition organizers summaries the results.", "labels": [], "entities": []}, {"text": "We will describe our systems in detail, including three single parsers in Section 2 and a voter in Section 3.", "labels": [], "entities": []}, {"text": "We focus on two novel technical contributions: the Cascaded BiLSTM model and the Reparsing strategy.", "labels": [], "entities": [{"text": "Reparsing", "start_pos": 81, "end_pos": 90, "type": "TASK", "confidence": 0.92003333568573}]}, {"text": "In Section 4 we will present experimental setup and results.", "labels": [], "entities": []}], "datasetContent": [], "tableCaptions": [{"text": " Table 1: Sentence number in training, dev, and test sets  for English, German and French UCCA data sets.", "labels": [], "entities": [{"text": "UCCA data sets", "start_pos": 90, "end_pos": 104, "type": "DATASET", "confidence": 0.8875884612401327}]}, {"text": " Table 2: F1 scores for both closed and open tracks in SemEval Task 1 2019 competition. The italic text represents  our official submission in competition and the bold text represents our best F1 scores.", "labels": [], "entities": [{"text": "F1", "start_pos": 10, "end_pos": 12, "type": "METRIC", "confidence": 0.9993739724159241}, {"text": "SemEval Task 1 2019 competition", "start_pos": 55, "end_pos": 86, "type": "TASK", "confidence": 0.7353845000267029}, {"text": "F1", "start_pos": 193, "end_pos": 195, "type": "METRIC", "confidence": 0.9979619979858398}]}, {"text": " Table 3: F1 scores on unlabeled data.", "labels": [], "entities": [{"text": "F1 scores", "start_pos": 10, "end_pos": 19, "type": "METRIC", "confidence": 0.9671866297721863}]}, {"text": " Table 3. We hypothesize there are  two reasons: 1. The conversion process could un-", "labels": [], "entities": [{"text": "conversion", "start_pos": 56, "end_pos": 66, "type": "TASK", "confidence": 0.9795621633529663}]}]}