{"title": [{"text": "Content Aggregation in Natural Language Hypertext Summarization of OLAP and Data Mining Discoveries", "labels": [], "entities": [{"text": "Content Aggregation", "start_pos": 0, "end_pos": 19, "type": "TASK", "confidence": 0.6789063364267349}, {"text": "Data Mining Discoveries", "start_pos": 76, "end_pos": 99, "type": "TASK", "confidence": 0.7492426832516988}]}], "abstractContent": [{"text": "We present anew approach to paratactic content aggregation in the context of generating hypertext summaries of OLAP and data mining discoveries.", "labels": [], "entities": [{"text": "paratactic content aggregation", "start_pos": 28, "end_pos": 58, "type": "TASK", "confidence": 0.7702582279841105}]}, {"text": "Two key properties make this approach innovative and interesting: (1) it encapsulates aggregation inside the sentence planning component, and (2) it relies on a domain independent algorithm working on a data structure that abstracts from lexical and syntactic knowledge.", "labels": [], "entities": []}], "introductionContent": [], "datasetContent": [], "tableCaptions": []}