{"title": [], "abstractContent": [{"text": "In this paper the experience made through the development of a NAtural Language driven Image Generation is discussed.", "labels": [], "entities": [{"text": "NAtural Language driven Image Generation", "start_pos": 63, "end_pos": 103, "type": "TASK", "confidence": 0.539525055885315}]}, {"text": "This system is able to imagine a static scene described by means of a sequence of simple phrases.", "labels": [], "entities": []}, {"text": "In particular, a theory for equilibrium and support will be outlined together with the problem of object positioning.", "labels": [], "entities": [{"text": "object positioning", "start_pos": 98, "end_pos": 116, "type": "TASK", "confidence": 0.7790077030658722}]}], "introductionContent": [], "datasetContent": [], "tableCaptions": []}