{"title": [{"text": "Computati nal Lingu\" t\" 0 IS lCS Articles Translating Collocations for Bilingual Lexicons: A Statistical Approach A Maximum Entropy Approach to Natural I~anguage Processing Error-tolerant Finite-state Recognition with Applications to Morphological Analysis and Spelling Correction From Conceptual Time to Linguistic Time Book Reviews Head-driven Phrase Structure Grammar Reviewed by", "labels": [], "entities": [{"text": "Morphological Analysis", "start_pos": 234, "end_pos": 256, "type": "TASK", "confidence": 0.7169958651065826}]}], "abstractContent": [], "introductionContent": [], "datasetContent": [], "tableCaptions": []}