{"title": [], "abstractContent": [{"text": "Morphotactics and allomorphy are usually modeled in different components, leading to interface problems.", "labels": [], "entities": []}, {"text": "To describe both uniformly, we define finite automata (FA) for allomorphy in the same feature description language used for morphotactics.", "labels": [], "entities": []}, {"text": "Nonphonologically conditioned allomorphy is problematic in FA models but submits readily to treatment in a uniform formalism .", "labels": [], "entities": [{"text": "FA", "start_pos": 59, "end_pos": 61, "type": "TASK", "confidence": 0.9430114030838013}]}], "introductionContent": [], "datasetContent": [], "tableCaptions": []}