{"title": [{"text": "EUEOTRA PRACTICAL EIPERIKI~K WITll A MOLTILINGUAL NACHINE T~LATION SYSTI0m UNDER DI~ELOPMKlqT", "labels": [], "entities": [{"text": "K WITll A MOLTILINGUAL NACHINE T", "start_pos": 27, "end_pos": 59, "type": "METRIC", "confidence": 0.8029526174068451}, {"text": "LATION SYSTI0m UNDER DI", "start_pos": 60, "end_pos": 83, "type": "METRIC", "confidence": 0.7826564311981201}, {"text": "ELOPMKlqT", "start_pos": 84, "end_pos": 93, "type": "METRIC", "confidence": 0.9417709112167358}]}], "abstractContent": [], "introductionContent": [], "datasetContent": [], "tableCaptions": []}