{"title": [{"text": "Computational Linguistics Articles Automatic Text Categorization in Terms of Genre and Author Bidirectional Contextual Resolution An Empirically Based System for Processing Definite Descriptions Learning Methods to Combine Linguistic Indicators: Improving Aspectual Classification and Revealing Linguistic Insights Squibs and Discussions On Coreferring: Coreference in MUC and Related Annotation Schemes Book Reviews Speech and Language Processing: An Introduction to Natural Language Processing, Computational Linguistics, and Speech Recognition Inside the Mind of BRUTUS, a Storytelling Machine Architectures and Mechanisms for Language Processing edited by", "labels": [], "entities": [{"text": "Bidirectional Contextual Resolution", "start_pos": 94, "end_pos": 129, "type": "TASK", "confidence": 0.7059099078178406}, {"text": "Improving Aspectual Classification", "start_pos": 246, "end_pos": 280, "type": "TASK", "confidence": 0.6037846903006235}, {"text": "Revealing Linguistic Insights Squibs and Discussions", "start_pos": 285, "end_pos": 337, "type": "TASK", "confidence": 0.7471069196859995}, {"text": "Speech Recognition", "start_pos": 528, "end_pos": 546, "type": "TASK", "confidence": 0.7473417222499847}]}], "abstractContent": [], "introductionContent": [], "datasetContent": [], "tableCaptions": []}