{"title": [{"text": "Extracting\ud97b\udf59Key\ud97b\udf59Semantic\ud97b\udf59Terms\ud97b\udf59from\ud97b\udf59Chinese\ud97b\udf59Speech\ud97b\udf59Query\ud97b\udf59for\ud97b\udf59Web\ud97b\udf59 Searches\ud97b\udf59 \ud97b\udf59 Gang\ud97b\udf59WANG\ud97b\udf59 \ud97b\udf59 \ud97b\udf59 Tat-Seng\ud97b\udf59CHUA\ud97b\udf59\ud97b\udf59\ud97b\udf59", "labels": [], "entities": [{"text": "Extracting\ud97b\udf59Key\ud97b\udf59Semantic\ud97b\udf59Terms\ud97b\udf59from\ud97b\udf59Chinese\ud97b\udf59Speech\ud97b\udf59Query", "start_pos": 0, "end_pos": 55, "type": "TASK", "confidence": 0.8819901982943217}, {"text": "\ud97b\udf59WANG\ud97b\udf59 \ud97b\udf59 \ud97b\udf59 Tat-Seng\ud97b\udf59CHUA", "start_pos": 81, "end_pos": 105, "type": "DATASET", "confidence": 0.7838304918259382}]}], "abstractContent": [], "introductionContent": [], "datasetContent": [{"text": "As\ud97b\udf59 our\ud97b\udf59 system\ud97b\udf59 aims\ud97b\udf59 to\ud97b\udf59 correct\ud97b\udf59 the\ud97b\udf59 errors\ud97b\udf59 and\ud97b\udf59 extract\ud97b\udf59CSS\ud97b\udf59 components\ud97b\udf59in\ud97b\udf59 spoken\ud97b\udf59 queries,\ud97b\udf59 it\ud97b\udf59 is\ud97b\udf59 important\ud97b\udf59 to\ud97b\udf59 demonstrate\ud97b\udf59 that\ud97b\udf59 our\ud97b\udf59 system\ud97b\udf59 is\ud97b\udf59 able\ud97b\udf59 to\ud97b\udf59 handle\ud97b\udf59 queries\ud97b\udf59 of\ud97b\udf59 different\ud97b\udf59 characteristics.\ud97b\udf59 To\ud97b\udf59 this\ud97b\udf59 end,\ud97b\udf59we\ud97b\udf59devised\ud97b\udf59two\ud97b\udf59sets\ud97b\udf59of\ud97b\udf59test\ud97b\udf59queries\ud97b\udf59as\ud97b\udf59follows.\ud97b\udf59 a)\ud97b\udf59 \ud97b\udf59Corpus\ud97b\udf59with\ud97b\udf59short\ud97b\udf59queries\ud97b\udf59 We\ud97b\udf59 devised\ud97b\udf59 10\ud97b\udf59 queries,\ud97b\udf59 each\ud97b\udf59 containing\ud97b\udf59 a\ud97b\udf59 CSS\ud97b\udf59 with\ud97b\udf59only\ud97b\udf59one\ud97b\udf59basic\ud97b\udf59component.\ud97b\udf59This\ud97b\udf59is\ud97b\udf59the\ud97b\udf59typical\ud97b\udf59 type\ud97b\udf59of\ud97b\udf59queries\ud97b\udf59posed\ud97b\udf59by\ud97b\udf59the\ud97b\udf59users\ud97b\udf59on\ud97b\udf59the\ud97b\udf59web.\ud97b\udf59We\ud97b\udf59 asked\ud97b\udf59 10\ud97b\udf59 different\ud97b\udf59 people\ud97b\udf59 to\ud97b\udf59 \"speak\"\ud97b\udf59 the\ud97b\udf59 queries,\ud97b\udf59 and\ud97b\udf59 used\ud97b\udf59 the\ud97b\udf59 IBM\ud97b\udf59 ViaVoice\ud97b\udf59 98\ud97b\udf59 to\ud97b\udf59 perform\ud97b\udf59 the\ud97b\udf59 speech\ud97b\udf59to\ud97b\udf59text\ud97b\udf59conversion.\ud97b\udf59This\ud97b\udf59gives\ud97b\udf59rise\ud97b\udf59to\ud97b\udf59a\ud97b\udf59col-lection\ud97b\udf59 of\ud97b\udf59 100\ud97b\udf59 spoken\ud97b\udf59 queries.\ud97b\udf59 There\ud97b\udf59 is\ud97b\udf59 a\ud97b\udf59 total\ud97b\udf59 of\ud97b\udf59 1,340\ud97b\udf59Chinese\ud97b\udf59characters\ud97b\udf59in\ud97b\udf59the\ud97b\udf59test\ud97b\udf59queries\ud97b\udf59with\ud97b\udf59a\ud97b\udf59 speech\ud97b\udf59recognition\ud97b\udf59error\ud97b\udf59rate\ud97b\udf59of\ud97b\udf5932.5%.\ud97b\udf59 b)\ud97b\udf59Corpus\ud97b\udf59with\ud97b\udf59long\ud97b\udf59queries\ud97b\udf59 In\ud97b\udf59 order\ud97b\udf59 to\ud97b\udf59 test\ud97b\udf59 on\ud97b\udf59 queries\ud97b\udf59 used\ud97b\udf59 in\ud97b\udf59 standard\ud97b\udf59 test\ud97b\udf59 corpuses,\ud97b\udf59 we\ud97b\udf59 adopted\ud97b\udf59 the\ud97b\udf59 query\ud97b\udf59 topics\ud97b\udf59 (1-10)\ud97b\udf59 employed\ud97b\udf59 in\ud97b\udf59 TREC-5\ud97b\udf59 Chinese-Language\ud97b\udf59 track.\ud97b\udf59 Here\ud97b\udf59 each\ud97b\udf59 query\ud97b\udf59 contains\ud97b\udf59 more\ud97b\udf59 than\ud97b\udf59 one\ud97b\udf59 key\ud97b\udf59 semantic\ud97b\udf59 component.\ud97b\udf59 We\ud97b\udf59 rephrased\ud97b\udf59 the\ud97b\udf59 queries\ud97b\udf59 into\ud97b\udf59 natural\ud97b\udf59 language\ud97b\udf59 query\ud97b\udf59 format,\ud97b\udf59 and\ud97b\udf59asked\ud97b\udf59twelve\ud97b\udf59 subjects\ud97b\udf59 to\ud97b\udf59 \"read\"\ud97b\udf59 the\ud97b\udf59 queries.", "labels": [], "entities": [{"text": "\ud97b\udf59 ViaVoice\ud97b\udf59 98", "start_pos": 548, "end_pos": 562, "type": "DATASET", "confidence": 0.826914593577385}, {"text": "\ud97b\udf59 speech\ud97b\udf59to\ud97b\udf59text\ud97b\udf59conversion.", "start_pos": 580, "end_pos": 608, "type": "TASK", "confidence": 0.7427214905619621}, {"text": "\ud97b\udf59 speech\ud97b\udf59recognition\ud97b\udf59error\ud97b\udf59rate", "start_pos": 746, "end_pos": 777, "type": "METRIC", "confidence": 0.6907375156879425}, {"text": "\ud97b\udf59 TREC-5\ud97b\udf59 Chinese-Language\ud97b\udf59 track.", "start_pos": 942, "end_pos": 976, "type": "DATASET", "confidence": 0.7751476864020029}]}], "tableCaptions": []}