{"title": [{"text": "xvii + 338 pp. (Studies in cognitive systems 4) Hardbound, ISBN 0-7923-0505-1, $63.00, Dfl 160.00, \u00a353", "labels": [], "entities": [{"text": "Hardbound", "start_pos": 48, "end_pos": 57, "type": "DATASET", "confidence": 0.9441247582435608}, {"text": "Dfl", "start_pos": 87, "end_pos": 90, "type": "METRIC", "confidence": 0.9796139001846313}]}], "abstractContent": [{"text": "Briefly Noted Books Received book itself persistently uses an ASCII hyphen where longer, non-ASCII dashes would be correct.)", "labels": [], "entities": []}, {"text": "Nor does the lengthy chapter on text formatting include discussion of good or bad typogra-phy or layout, or what features such systems need for the user to achieve attractive documents.", "labels": [], "entities": [{"text": "text formatting", "start_pos": 32, "end_pos": 47, "type": "TASK", "confidence": 0.7300749123096466}]}, {"text": "(The book's typesetting is not too bad, but the leading is a tad too tight, the paragraph spacing two tads too loose.", "labels": [], "entities": []}, {"text": "The layout is based on the elegant MIT Press house style, but there are many widows and orphans, and figures are often very poorly placed and hard to distinguish from the text.)", "labels": [], "entities": [{"text": "MIT Press house", "start_pos": 35, "end_pos": 50, "type": "DATASET", "confidence": 0.9250390926996866}]}, {"text": "The book is oriented strongly toward Unix and its text-processing tools.", "labels": [], "entities": []}, {"text": "Although primarily intended as an undergraduate textbook (pun unavoidable), it may also serve as a useful reference work for its summary of techniques in encryption, hyphenation, and the like.-G.H.", "labels": [], "entities": []}, {"text": "BOOKS RECEIVED Books listed below that are marked with a ~r will be reviewed in a future issue.: The MIT Press, 1990, xii + 270 pp.", "labels": [], "entities": [{"text": "BOOKS RECEIVED", "start_pos": 0, "end_pos": 14, "type": "METRIC", "confidence": 0.7424570620059967}, {"text": "The MIT Press, 1990", "start_pos": 97, "end_pos": 116, "type": "DATASET", "confidence": 0.7807950377464294}]}, {"text": "Hard-bound, ISBN 0-262-06130-9, $29.95 tPractical SGML Eric van Herwijnen (CERN) Dordrecht: Kluwer Academic Publishers, 1990, xviii + 307 pp.", "labels": [], "entities": [{"text": "SGML Eric van Herwijnen (CERN) Dordrecht: Kluwer Academic Publishers, 1990", "start_pos": 50, "end_pos": 124, "type": "DATASET", "confidence": 0.5677838006189891}]}, {"text": "Paperbound, ISBN 0-7923-0635-X, $39.95 tA Computational Model of Metaphor Interpretation", "labels": [], "entities": [{"text": "Computational Model of Metaphor Interpretation", "start_pos": 42, "end_pos": 88, "type": "TASK", "confidence": 0.5244079053401947}]}], "introductionContent": [], "datasetContent": [], "tableCaptions": []}