{"title": [{"text": "ACL 1988 DUES STATEMENT AND MEMBERSHIP APPLICATION Institutions Now Order Journals from MIT Press; New LATE PAYMENT FEE for Late Renewals", "labels": [], "entities": [{"text": "ACL 1988 DUES STATEMENT", "start_pos": 0, "end_pos": 23, "type": "TASK", "confidence": 0.4409923776984215}, {"text": "MEMBERSHIP APPLICATION", "start_pos": 28, "end_pos": 50, "type": "TASK", "confidence": 0.6665074229240417}, {"text": "FEE", "start_pos": 116, "end_pos": 119, "type": "METRIC", "confidence": 0.8197299242019653}]}], "abstractContent": [], "introductionContent": [], "datasetContent": [], "tableCaptions": []}